Metadata-Version: 2.1
Name: opengame
Version: 1.0.5
Home-page: https://github.com/stripepython/KittenScript/
Author: stripe-python
Author-email: stripe-python@139.com
Maintainer: stripe-python
Maintainer-email: stripe-python@139.com
License: MIT License
Classifier: Programming Language :: Python :: 3
Classifier: License :: OSI Approved :: MIT License
Classifier: Operating System :: OS Independent
License-File: LICENSE
Requires-Dist: click
